[
{
    "model": "server.machine",
    "pk": 1,
    "fields": {
        "machine_group": 1,
        "serial": "C0DEADBEEF",
        "hostname": "mla680",
        "operating_system": "10.12",
        "memory": "16 GB",
        "memory_kb": 16777216,
        "munki_version": "2.8.1.2845",
        "manifest": "C0DEADBEEF",
        "hd_space": 476429672000,
        "hd_total": 975912960000,
        "hd_percent": "51",
        "console_user": "shcrai",
        "machine_model": "MacBookPro11,5",
        "machine_model_friendly": "MacBook Pro (Retina, 15-inch, Mid 2015)",
        "cpu_type": "Intel Core i7",
        "cpu_speed": "2.5 GHz",
        "os_family": "Darwin",
        "last_checkin": "2016-10-06T19:29:38.376Z",
        "first_checkin": "2016-10-06T15:51:21.145Z",
        "sal_version": "1.0.6",
        "deployed": true,
        "broken_client": false
    }
},
{
    "model": "server.machine",
    "pk": 2,
    "fields": {
        "machine_group": 1,
        "serial": "C1DEADBEEF",
        "hostname": "mla806",
        "operating_system": "10.12.5",
        "memory": "16 GB",
        "memory_kb": 16777216,
        "munki_version": "2.8.2.2855",
        "manifest": "C1DEADBEEF",
        "hd_space": 536276480000,
        "hd_total": 975831040000,
        "hd_percent": "45",
        "console_user": "shcrai",
        "machine_model": "MacBookPro13,3",
        "machine_model_friendly": "MacBook Pro (15-inch, 2016)",
        "cpu_type": "Intel Core i7",
        "cpu_speed": "2.7 GHz",
        "os_family": "Darwin",
        "last_checkin": "2017-05-16T19:04:51.336Z",
        "first_checkin": "2017-05-16T19:04:51.728Z",
        "sal_version": "2.0.3",
        "deployed": true,
        "broken_client": false
    }
}
]
